{"created-date": {"value": 1468229999472}, "last-modified-date": {"value": 1468229999472}, "source": {"source-orcid": null, "source-client-id": {"uri": "http://orcid.org/client/0000-0002-5982-8983", "path": "0000-0002-5982-8983", "host": "orcid.org"}, "source-name": {"value": "Scopus - Elsevier"}}, "put-code": 25306962, "path": "/0000-0002-9785-7726/work/25306962", "title": {"title": {"value": "MINUTE-TIMESCALE &gt;100 MeV \u03b3-RAY VARIABILITY during the GIANT OUTBURST of QUASAR 3C 279 OBSERVED by FERMI-LAT in 2015 June"}, "subtitle": null, "translated-title": null}, "journal-title": {"value": "Astrophysical Journal Letters"}, "short-description": null, "citation": {"citation-type": "BIBTEX", "citation-value": "@article{Baldini2016,title = {MINUTE-TIMESCALE \\&gt;100 MeV ?-RAY VARIABILITY during the GIANT OUTBURST of QUASAR 3C 279 OBSERVED by FERMI-LAT in 2015 June},journal = {Astrophysical Journal Letters},year = {2016},volume = {824},number = {2},author = {Ackermann, M. and Anantua, R. and Asano, K. and Baldini, L. and Barbiellini, G. and Bastieri, D. and Gonzalez, J.B. and Bellazzini, R. and Bissaldi, E. and Blandford, R.D. and Bloom, E.D. and Bonino, R. and Bottacini, E. and Bruel, P. and Buehler, R. and Caliandro, G.A. and Cameron, R.A. and Caragiulo, M. and Caraveo, P.A. and Cavazzuti, E. and Cecchi, C. and Cheung, C.C. and Chiang, J. and Chiaro, G. and Ciprini, S. and Cohen-Tanugi, J. and Costanza, F. and Cutini, S. and D{'}Ammando, F. and Palma, F.D. and Desiante, R. and Digel, S.W. and Lalla, N.D. and Mauro, M.D. and Venere, L.D. and Drell, P.S. and Favuzzi, C. and Fegan, S.J. and Ferrara, E.C. and Fukazawa, Y. and Funk, S. and Fusco, P. and Gargano, F. and Gasparrini, D. and Giglietto, N. and Giordano, F. and Giroletti, M. and Grenier, I.A. and Guillemot, L. and Guiriec, S. and Hayashida, M. and Hays, E. and Horan, D. and J{\\'o}hannesson, G. and Kensei, S. and Kocevski, D. and Kuss, M. and Mura, G.L. and Larsson, S. and Latronico, L. and Li, J. and Longo, F. and Loparco, F. and Lott, B. and Lovellette, M.N. and Lubrano, P. and Madejski, G.M. and Magill, J.D. and Maldera, S. and Manfreda, A. and Mayer, M. and Mazziotta, M.N. and Michelson, P.F. and Mirabal, N. and Mizuno, T. and Monzani, M.E. and Morselli, A. and Moskalenko, I.V. and Nalewajko, K. and Negro, M. and Nuss, E. and Ohsugi, T. and Orlando, E. and Paneque, D. and Perkins, J.S. and Pesce-Rollins, M. and Piron, F. and Pivato, G. and Porter, T.A. and Principe, G. and Rando, R. and Razzano, M. and Razzaque, S. and Reimer, A. and Scargle, J.D. and Sgr, C. and Sikora, M. and Simone, D. and Siskind, E.J. and Spada, F. and Spinelli, P. and Stawarz, L. and Thayer, J.B. and Thompson, D.J. and Torres, D.F. and Troja, E. and Uchiyama, Y. and Yuan, Y. and Zimmer, S.}}"}, "type": "JOURNAL_ARTICLE", "publication-date": {"year": {"value": "2016"}, "month": null, "day": null, "media-type": null}, "external-ids": {"external-id": [{"external-id-type": "doi", "external-id-value": "10.3847/2041-8205/824/2/L20", "external-id-url": null, "external-id-relationship": "SELF"}, {"external-id-type": "eid", "external-id-value": "2-s2.0-84976367258", "external-id-url": null, "external-id-relationship": "SELF"}]}, "url": {"value": "http://www.scopus.com/inward/record.url?eid=2-s2.0-84976367258&partnerID=MN8TOARS"}, "contributors": {"contributor": [{"contributor-orcid": null, "credit-name": {"value": "Ackermann, M."}, "contributor-email": null, "contributor-attributes": null}, {"contributor-orcid": null, "credit-name": {"value": "Anantua, R."}, "contributor-email": null, "contributor-attributes": null}, {"contributor-orcid": null, "credit-name": {"value": "Asano, K."}, "contributor-email": null, "contributor-attributes": null}, {"contributor-orcid": null, "credit-name": {"value": "Baldini, L."}, "contributor-email": null, "contributor-attributes": null}, {"contributor-orcid": null, "credit-name": {"value": "Barbiellini, G."}, "contributor-email": null, "contributor-attributes": null}, {"contributor-orcid": null, "credit-name": {"value": "Bastieri, D."}, "contributor-email": null, "contributor-attributes": null}, {"contributor-orcid": null, "credit-name": {"value": "Gonzalez, J.B."}, "contributor-email": null, "contributor-attributes": null}, {"contributor-orcid": null, "credit-name": {"value": "Bellazzini, R."}, "contributor-email": null, "contributor-attributes": null}, {"contributor-orcid": null, "credit-name": {"value": "Bissaldi, E."}, "contributor-email": null, "contributor-attributes": null}, {"contributor-orcid": null, "credit-name": {"value": "Blandford, R.D."}, "contributor-email": null, "contributor-attributes": null}, {"contributor-orcid": null, "credit-name": {"value": "Bloom, E.D."}, "contributor-email": null, "contributor-attributes": null}, {"contributor-orcid": null, "credit-name": {"value": "Bonino, R."}, "contributor-email": null, "contributor-attributes": null}, {"contributor-orcid": null, "credit-name": {"value": "Bottacini, E."}, "contributor-email": null, "contributor-attributes": null}, {"contributor-orcid": null, "credit-name": {"value": "Bruel, P."}, "contributor-email": null, "contributor-attributes": null}, {"contributor-orcid": null, "credit-name": {"value": "Buehler, R."}, "contributor-email": null, "contributor-attributes": null}, {"contributor-orcid": null, "credit-name": {"value": "Caliandro, G.A."}, "contributor-email": null, "contributor-attributes": null}, {"contributor-orcid": null, "credit-name": {"value": "Cameron, R.A."}, "contributor-email": null, "contributor-attributes": null}, {"contributor-orcid": null, "credit-name": {"value": "Caragiulo, M."}, "contributor-email": null, "contributor-attributes": null}, {"contributor-orcid": null, "credit-name": {"value": "Caraveo, P.A."}, "contributor-email": null, "contributor-attributes": null}, {"contributor-orcid": null, "credit-name": {"value": "Cavazzuti, E."}, "contributor-email": null, "contributor-attributes": null}, {"contributor-orcid": null, "credit-name": {"value": "Cecchi, C."}, "contributor-email": null, "contributor-attributes": null}, {"contributor-orcid": null, "credit-name": {"value": "Cheung, C.C."}, "contributor-email": null, "contributor-attributes": null}, {"contributor-orcid": null, "credit-name": {"value": "Chiang, J."}, "contributor-email": null, "contributor-attributes": null}, {"contributor-orcid": null, "credit-name": {"value": "Chiaro, G."}, "contributor-email": null, "contributor-attributes": null}, {"contributor-orcid": null, "credit-name": {"value": "Ciprini, S."}, "contributor-email": null, "contributor-attributes": null}, {"contributor-orcid": null, "credit-name": {"value": "Cohen-Tanugi, J."}, "contributor-email": null, "contributor-attributes": null}, {"contributor-orcid": null, "credit-name": {"value": "Costanza, F."}, "contributor-email": null, "contributor-attributes": null}, {"contributor-orcid": null, "credit-name": {"value": "Cutini, S."}, "contributor-email": null, "contributor-attributes": null}, {"contributor-orcid": null, "credit-name": {"value": "D'Ammando, F."}, "contributor-email": null, "contributor-attributes": null}, {"contributor-orcid": null, "credit-name": {"value": "Palma, F.D."}, "contributor-email": null, "contributor-attributes": null}, {"contributor-orcid": null, "credit-name": {"value": "Desiante, R."}, "contributor-email": null, "contributor-attributes": null}, {"contributor-orcid": null, "credit-name": {"value": "Digel, S.W."}, "contributor-email": null, "contributor-attributes": null}, {"contributor-orcid": null, "credit-name": {"value": "Lalla, N.D."}, "contributor-email": null, "contributor-attributes": null}, {"contributor-orcid": null, "credit-name": {"value": "Mauro, M.D."}, "contributor-email": null, "contributor-attributes": null}, {"contributor-orcid": null, "credit-name": {"value": "Venere, L.D."}, "contributor-email": null, "contributor-attributes": null}, {"contributor-orcid": null, "credit-name": {"value": "Drell, P.S."}, "contributor-email": null, "contributor-attributes": null}, {"contributor-orcid": null, "credit-name": {"value": "Favuzzi, C."}, "contributor-email": null, "contributor-attributes": null}, {"contributor-orcid": null, "credit-name": {"value": "Fegan, S.J."}, "contributor-email": null, "contributor-attributes": null}, {"contributor-orcid": null, "credit-name": {"value": "Ferrara, E.C."}, "contributor-email": null, "contributor-attributes": null}, {"contributor-orcid": null, "credit-name": {"value": "Fukazawa, Y."}, "contributor-email": null, "contributor-attributes": null}, {"contributor-orcid": null, "credit-name": {"value": "Funk, S."}, "contributor-email": null, "contributor-attributes": null}, {"contributor-orcid": null, "credit-name": {"value": "Fusco, P."}, "contributor-email": null, "contributor-attributes": null}, {"contributor-orcid": null, "credit-name": {"value": "Gargano, F."}, "contributor-email": null, "contributor-attributes": null}, {"contributor-orcid": null, "credit-name": {"value": "Gasparrini, D."}, "contributor-email": null, "contributor-attributes": null}, {"contributor-orcid": null, "credit-name": {"value": "Giglietto, N."}, "contributor-email": null, "contributor-attributes": null}, {"contributor-orcid": null, "credit-name": {"value": "Giordano, F."}, "contributor-email": null, "contributor-attributes": null}, {"contributor-orcid": null, "credit-name": {"value": "Giroletti, M."}, "contributor-email": null, "contributor-attributes": null}, {"contributor-orcid": null, "credit-name": {"value": "Grenier, I.A."}, "contributor-email": null, "contributor-attributes": null}, {"contributor-orcid": null, "credit-name": {"value": "Guillemot, L."}, "contributor-email": null, "contributor-attributes": null}, {"contributor-orcid": null, "credit-name": {"value": "Guiriec, S."}, "contributor-email": null, "contributor-attributes": null}, {"contributor-orcid": null, "credit-name": {"value": "Hayashida, M."}, "contributor-email": null, "contributor-attributes": null}, {"contributor-orcid": null, "credit-name": {"value": "Hays, E."}, "contributor-email": null, "contributor-attributes": null}, {"contributor-orcid": null, "credit-name": {"value": "Horan, D."}, "contributor-email": null, "contributor-attributes": null}, {"contributor-orcid": null, "credit-name": {"value": "J\u00f3hannesson, G."}, "contributor-email": null, "contributor-attributes": null}, {"contributor-orcid": null, "credit-name": {"value": "Kensei, S."}, "contributor-email": null, "contributor-attributes": null}, {"contributor-orcid": null, "credit-name": {"value": "Kocevski, D."}, "contributor-email": null, "contributor-attributes": null}, {"contributor-orcid": null, "credit-name": {"value": "Kuss, M."}, "contributor-email": null, "contributor-attributes": null}, {"contributor-orcid": null, "credit-name": {"value": "Mura, G.L."}, "contributor-email": null, "contributor-attributes": null}, {"contributor-orcid": null, "credit-name": {"value": "Larsson, S."}, "contributor-email": null, "contributor-attributes": null}, {"contributor-orcid": null, "credit-name": {"value": "Latronico, L."}, "contributor-email": null, "contributor-attributes": null}, {"contributor-orcid": null, "credit-name": {"value": "Li, J."}, "contributor-email": null, "contributor-attributes": null}, {"contributor-orcid": null, "credit-name": {"value": "Longo, F."}, "contributor-email": null, "contributor-attributes": null}, {"contributor-orcid": null, "credit-name": {"value": "Loparco, F."}, "contributor-email": null, "contributor-attributes": null}, {"contributor-orcid": null, "credit-name": {"value": "Lott, B."}, "contributor-email": null, "contributor-attributes": null}, {"contributor-orcid": null, "credit-name": {"value": "Lovellette, M.N."}, "contributor-email": null, "contributor-attributes": null}, {"contributor-orcid": null, "credit-name": {"value": "Lubrano, P."}, "contributor-email": null, "contributor-attributes": null}, {"contributor-orcid": null, "credit-name": {"value": "Madejski, G.M."}, "contributor-email": null, "contributor-attributes": null}, {"contributor-orcid": null, "credit-name": {"value": "Magill, J.D."}, "contributor-email": null, "contributor-attributes": null}, {"contributor-orcid": null, "credit-name": {"value": "Maldera, S."}, "contributor-email": null, "contributor-attributes": null}, {"contributor-orcid": null, "credit-name": {"value": "Manfreda, A."}, "contributor-email": null, "contributor-attributes": null}, {"contributor-orcid": null, "credit-name": {"value": "Mayer, M."}, "contributor-email": null, "contributor-attributes": null}, {"contributor-orcid": null, "credit-name": {"value": "Mazziotta, M.N."}, "contributor-email": null, "contributor-attributes": null}, {"contributor-orcid": null, "credit-name": {"value": "Michelson, P.F."}, "contributor-email": null, "contributor-attributes": null}, {"contributor-orcid": null, "credit-name": {"value": "Mirabal, N."}, "contributor-email": null, "contributor-attributes": null}, {"contributor-orcid": null, "credit-name": {"value": "Mizuno, T."}, "contributor-email": null, "contributor-attributes": null}, {"contributor-orcid": null, "credit-name": {"value": "Monzani, M.E."}, "contributor-email": null, "contributor-attributes": null}, {"contributor-orcid": null, "credit-name": {"value": "Morselli, A."}, "contributor-email": null, "contributor-attributes": null}, {"contributor-orcid": null, "credit-name": {"value": "Moskalenko, I.V."}, "contributor-email": null, "contributor-attributes": null}, {"contributor-orcid": null, "credit-name": {"value": "Nalewajko, K."}, "contributor-email": null, "contributor-attributes": null}, {"contributor-orcid": null, "credit-name": {"value": "Negro, M."}, "contributor-email": null, "contributor-attributes": null}, {"contributor-orcid": null, "credit-name": {"value": "Nuss, E."}, "contributor-email": null, "contributor-attributes": null}, {"contributor-orcid": null, "credit-name": {"value": "Ohsugi, T."}, "contributor-email": null, "contributor-attributes": null}, {"contributor-orcid": null, "credit-name": {"value": "Orlando, E."}, "contributor-email": null, "contributor-attributes": null}, {"contributor-orcid": null, "credit-name": {"value": "Paneque, D."}, "contributor-email": null, "contributor-attributes": null}, {"contributor-orcid": null, "credit-name": {"value": "Perkins, J.S."}, "contributor-email": null, "contributor-attributes": null}, {"contributor-orcid": null, "credit-name": {"value": "Pesce-Rollins, M."}, "contributor-email": null, "contributor-attributes": null}, {"contributor-orcid": null, "credit-name": {"value": "Piron, F."}, "contributor-email": null, "contributor-attributes": null}, {"contributor-orcid": null, "credit-name": {"value": "Pivato, G."}, "contributor-email": null, "contributor-attributes": null}, {"contributor-orcid": null, "credit-name": {"value": "Porter, T.A."}, "contributor-email": null, "contributor-attributes": null}, {"contributor-orcid": null, "credit-name": {"value": "Principe, G."}, "contributor-email": null, "contributor-attributes": null}, {"contributor-orcid": null, "credit-name": {"value": "Rando, R."}, "contributor-email": null, "contributor-attributes": null}, {"contributor-orcid": null, "credit-name": {"value": "Razzano, M."}, "contributor-email": null, "contributor-attributes": null}, {"contributor-orcid": null, "credit-name": {"value": "Razzaque, S."}, "contributor-email": null, "contributor-attributes": null}, {"contributor-orcid": null, "credit-name": {"value": "Reimer, A."}, "contributor-email": null, "contributor-attributes": null}, {"contributor-orcid": null, "credit-name": {"value": "Scargle, J.D."}, "contributor-email": null, "contributor-attributes": null}, {"contributor-orcid": null, "credit-name": {"value": "Sgr, C."}, "contributor-email": null, "contributor-attributes": null}, {"contributor-orcid": null, "credit-name": {"value": "Sikora, M."}, "contributor-email": null, "contributor-attributes": null}, {"contributor-orcid": null, "credit-name": {"value": "Simone, D."}, "contributor-email": null, "contributor-attributes": null}, {"contributor-orcid": null, "credit-name": {"value": "Siskind, E.J."}, "contributor-email": null, "contributor-attributes": null}, {"contributor-orcid": null, "credit-name": {"value": "Spada, F."}, "contributor-email": null, "contributor-attributes": null}, {"contributor-orcid": null, "credit-name": {"value": "Spinelli, P."}, "contributor-email": null, "contributor-attributes": null}, {"contributor-orcid": null, "credit-name": {"value": "Stawarz, L."}, "contributor-email": null, "contributor-attributes": null}, {"contributor-orcid": null, "credit-name": {"value": "Thayer, J.B."}, "contributor-email": null, "contributor-attributes": null}, {"contributor-orcid": null, "credit-name": {"value": "Thompson, D.J."}, "contributor-email": null, "contributor-attributes": null}, {"contributor-orcid": null, "credit-name": {"value": "Torres, D.F."}, "contributor-email": null, "contributor-attributes": null}, {"contributor-orcid": null, "credit-name": {"value": "Troja, E."}, "contributor-email": null, "contributor-attributes": null}, {"contributor-orcid": null, "credit-name": {"value": "Uchiyama, Y."}, "contributor-email": null, "contributor-attributes": null}, {"contributor-orcid": null, "credit-name": {"value": "Yuan, Y."}, "contributor-email": null, "contributor-attributes": null}, {"contributor-orcid": null, "credit-name": {"value": "Zimmer, S."}, "contributor-email": null, "contributor-attributes": null}]}, "language-code": null, "country": null, "visibility": "PUBLIC"}